kilter/service/__init__.py
kilter/service/options.py
kilter/service/py.typed
kilter/service/runner.py
kilter/service/session.py
kilter/service/util.py
kilter_service-0.3.1.dist-info/licenses/LICENCE.txt
kilter_service-0.3.1.dist-info/WHEEL
kilter_service-0.3.1.dist-info/METADATA
kilter_service-0.3.1.dist-info/RECORD
