Metadata-Version: 2.4
Name: kilter.service
Version: 0.3.1
Summary: High level, asynchronous framework for writing mail filters
Author-email: Dom Sekotill <dom.sekotill@kodo.org.uk>
Requires-Python: ~=3.11
Classifier: Development Status :: 1 - Planning
Classifier: Intended Audience :: Telecommunications Industry
Classifier: License :: OSI Approved :: Mozilla Public License 2.0 (MPL 2.0)
Classifier: Topic :: Communications :: Email :: Filters
License-File: LICENCE.txt
Requires-Dist: anyio ~=4.0
Requires-Dist: async-generator ~=1.2
Requires-Dist: kilter.protocol ~=0.6.0
Requires-Dist: typing-extensions ~=4.0
Requires-Dist: sphinx ~=5.0 ; extra == "docs"
Requires-Dist: myst-parser ; extra == "docs"
Requires-Dist: sphinx-rtd-theme ; extra == "docs"
Requires-Dist: trio ; extra == "tests"
Project-URL: Documentation, https://kilter.kodo.org.uk/kilter.service/
Project-URL: Issues, https://github.com/domsekotill/kilter.service/issues
Project-URL: Source, https://github.com/domsekotill/kilter.service
Provides-Extra: docs
Provides-Extra: tests
